LICENSE.txt
README.md
setup.cfg
setup.py
process_twarc/__init__.py
process_twarc/cluster.py
process_twarc/util.py
process_twarc.egg-info/PKG-INFO
process_twarc.egg-info/SOURCES.txt
process_twarc.egg-info/dependency_links.txt
process_twarc.egg-info/requires.txt
process_twarc.egg-info/top_level.txt
process_twarc/benchmark/__init__.py
process_twarc/benchmark/generative_ai.py
process_twarc/build_base_model/__init__.py
process_twarc/build_base_model/build_training_corpus.py
process_twarc/build_base_model/configure_base_model.py
process_twarc/corpus_analysis/__init__.py
process_twarc/corpus_analysis/calculate.py
process_twarc/corpus_analysis/count.py
process_twarc/corpus_analysis/ner.py
process_twarc/corpus_analysis/plot.py
process_twarc/corpus_analysis/pos.py
process_twarc/corpus_analysis/tabulate.py
process_twarc/simulate_tweet/__init__.py
process_twarc/simulate_tweet/default-pfp.png
process_twarc/simulate_tweet/generate.py
process_twarc/train/MLM.py
process_twarc/train/__init__.py
process_twarc/train/classifier.py
process_twarc/train/evaluate.py
process_twarc/train/preprocess.py
process_twarc/train/util.py