Metadata-Version: 2.1
Name: process-twarc
Version: 0.20.2
Summary: Tools for transforming raw data from Twarc2 to structured data for Masked Language Modeling.
Home-page: https://github.com/user/Lone-Wolfgang
Author: Jordan Wolfgang Klein
Author-email: jordan.klein.21@um.edu.mt
License: MIT
Keywords: Twitter,Deduplication,Tokenization,Language Modeling
Classifier: Development Status :: 3 - Alpha
Classifier: Intended Audience :: Developers
Classifier: Topic :: Software Development :: Build Tools
Classifier: License :: OSI Approved :: MIT License
Classifier: Programming Language :: Python :: 3.9
Classifier: Programming Language :: Python :: 3.10
License-File: LICENSE.txt
